CHANGES.txt
COPYRIGHT.txt
LICENSE.txt
README.txt
bootstrap.py
buildout.cfg
setup.py
src/z3c/__init__.py
src/z3c.proxy.egg-info/PKG-INFO
src/z3c.proxy.egg-info/SOURCES.txt
src/z3c.proxy.egg-info/dependency_links.txt
src/z3c.proxy.egg-info/namespace_packages.txt
src/z3c.proxy.egg-info/not-zip-safe
src/z3c.proxy.egg-info/requires.txt
src/z3c.proxy.egg-info/top_level.txt
src/z3c/proxy/README.txt
src/z3c/proxy/SETUP.cfg
src/z3c/proxy/__init__.py
src/z3c/proxy/container.py
src/z3c/proxy/interfaces.py
src/z3c/proxy/overrides.zcml
src/z3c/proxy/testing.py
src/z3c/proxy/tests.py
src/z3c/proxy/z3c.proxy-overrides.zcml