Metadata-Version: 1.0
Name: z3c.proxy
Version: 0.6.0
Summary: Container proxy implementation for Zope3
Home-page: http://cheeseshop.python.org/pypi/z3c.proxy
Author: Roger Ineichen, Stephan Richter and the Zope Community
Author-email: zope3-dev@zope.org
License: ZPL 2.1
Keywords: zope3 z3c container proxy
Platform: UNKNOWN
Classifier: Development Status :: 4 - Beta
Classifier: Environment :: Web Environment
Classifier: Intended Audience :: Developers
Classifier: License :: OSI Approved :: Zope Public License
Classifier: Programming Language :: Python
Classifier: Natural Language :: English
Classifier: Operating System :: OS Independent
Classifier: Topic :: Internet :: WWW/HTTP
Classifier: Framework :: Zope3
